himena_cryoem_io/__init__.py
himena_cryoem_io/_parse_nav.py
himena_cryoem_io/consts.py
himena_cryoem_io/fetch.py
himena_cryoem_io/io.py
himena_cryoem_io/star_meta.py
himena_cryoem_io/tools/__init__.py
himena_cryoem_io/tools/star.py
himena_cryoem_io/widgets/__init__.py
himena_cryoem_io/widgets/navigator.py
himena_cryoem_io/widgets/star.py
himena_cryoem_io-0.1.1.dist-info/METADATA
himena_cryoem_io-0.1.1.dist-info/WHEEL
himena_cryoem_io-0.1.1.dist-info/entry_points.txt
himena_cryoem_io-0.1.1.dist-info/licenses/LICENSE
himena_cryoem_io-0.1.1.dist-info/RECORD
