Metadata-Version: 2.4
Name: himena-cryoem-io
Version: 0.1.1
Summary: File readers and writers for cryo-EM
Project-URL: Documentation, https://github.com/hanjinliu/himena-cryoem-io#readme
Project-URL: Issues, https://github.com/hanjinliu/himena-cryoem-io/issues
Project-URL: Source, https://github.com/hanjinliu/himena-cryoem-io
Author-email: hanjinliu <liuhanjin.sc@gmail.com>
License: BSD 3-Clause License
License-File: LICENSE
Classifier: Development Status :: 4 - Beta
Classifier: Programming Language :: Python
Classifier: Programming Language :: Python :: 3.10
Classifier: Programming Language :: Python :: 3.11
Classifier: Programming Language :: Python :: 3.12
Classifier: Programming Language :: Python :: 3.13
Classifier: Programming Language :: Python :: 3.14
Classifier: Programming Language :: Python :: Implementation :: CPython
Classifier: Programming Language :: Python :: Implementation :: PyPy
Requires-Python: >=3.10
Requires-Dist: imodmodel>=0.1.0
Requires-Dist: mdocfile>=0.2.2
Requires-Dist: mrcfile
Requires-Dist: polars>=1.34.0
Requires-Dist: starfile-rs>=0.1.6
